santiq/__init__.py
santiq/cli/main.py
santiq/cli/commands/data_utils.py
santiq/cli/commands/plugin.py
santiq/cli/commands/run.py
santiq/core/__init__.py
santiq/core/audit.py
santiq/core/config.py
santiq/core/engine.py
santiq/core/exceptions.py
santiq/core/pipeline.py
santiq/core/plugin_manager.py
santiq/plugins/base/extractor.py
santiq/plugins/base/loader.py
santiq/plugins/base/profiler.py
santiq/plugins/base/transformer.py
santiq/plugins/extractors/csv_extractor.py
santiq/plugins/extractors/excel_extractor.py
santiq/plugins/extractors/json_extractor.py
santiq/plugins/loaders/csv_loader.py
santiq/plugins/loaders/excel_loader.py
santiq/plugins/loaders/json_loader.py
santiq/plugins/profilers/basic_profiler.py
santiq/plugins/transformers/basic_cleaner.py
santiq-0.1.5.dist-info/licenses/LICENSE
santiq-0.1.5.dist-info/METADATA
santiq-0.1.5.dist-info/WHEEL
santiq-0.1.5.dist-info/entry_points.txt
santiq-0.1.5.dist-info/top_level.txt
santiq-0.1.5.dist-info/RECORD
